[
  {
    "id": 1,
    "attribute": null,
    "created": "2017-09-30 20:22:55.698000",
    "data_teeth": "sadadadasd",
    "date_missing": null,
    "dressing": null,
    "history_medical": null,
    "modified": "2017-09-30 20:22:55.698000",
    "name_missingperson": "sapoman",
    "nationality": "th",
    "other": "asdadasd",
    "scar": "weertytyyyyr",
    "sex": "man",
    "tattoo": null,
    "time_missing": null
  },
  {
    "id": 2,
    "attribute": "",
    "created": "2017-09-30 21:02:28.421000",
    "data_teeth": "ฟันเหลือง",
    "date_missing": null,
    "dressing": "ใส่เสื้อสีขาว",
    "history_medical": "ไม่เคยเข้าโรงพยาบาล",
    "modified": "2017-09-30 21:02:28.421000",
    "name_missingperson": "jirapat birdmonn",
    "nationality": null,
    "other": "",
    "scar": "",
    "sex": "ชาย",
    "tattoo": "มังกร",
    "time_missing": null
  }
]